{
  "sorting": "ascending",
  "count_libraries": false,
  "compact_list": false,
  "count_children": false,
  "mods_button_style": "icon",
  "game_menu_button_style": "replace",
  "count_hidden_mods": false,
  "mod_count_location": "title_screen",
  "hide_mod_links": true,
  "show_libraries": false,
  "hide_mod_license": true,
  "hide_badges": true,
  "hide_mod_credits": false,
  "easter_eggs": false,
  "random_java_colors": false,
  "translate_names": true,
  "translate_descriptions": true,
  "update_checker": false,
  "button_update_badge": false,
  "update_channel": "release",
  "quick_configure": true,
  "modify_title_screen": true,
  "modify_game_menu": true,
  "hide_config_buttons": false,
  "config_mode": false,
  "disable_drag_and_drop": false,
  "hidden_mods": [
  "minecraft",
	"malilib",
	"octolib",
	"supermartijn642configlib",
	"tr7zw-api-parent",
	"lambdynlights_api",
	"lambdynlights_runtime",
	"error_notifier",
	"polydex",
	"polydex2rei",
	"polymer-bundled",
	"server_translations_api",
	"sidebar-api",
	"tcdcommons",
  "commandaliases",
	"crash_assistant",
	"net_raphimc_noteblocklib",
	"translationfallbacks",
	"journeymap-api-fabric",
	"ar_com_hjg_pngj",
	"org_redlance_platformtools",
	"online_emotes",
  "darkwindowbar"
  ],
  "hidden_configs": [],
  "disable_update_checker": []
}